json_maj/__init__.py
json_maj/cli.py
json_maj/create_executable.py
json_maj/main.py
json_maj-0.0.8.dist-info/METADATA
json_maj-0.0.8.dist-info/WHEEL
json_maj-0.0.8.dist-info/entry_points.txt
json_maj-0.0.8.dist-info/RECORD
