Metadata-Version: 2.1
Name: json-maj
Version: 0.0.8
Summary: Updates Jsons w/ json, key pair, or entire dictionary as arguments
License: MIT
Author: anthony galassi
Author-email: 28850131+bendhouseart@users.noreply.github.com
Requires-Python: >=3.5,<4.0
Classifier: License :: OSI Approved :: MIT License
Classifier: Programming Language :: Python :: 3
Classifier: Programming Language :: Python :: 3.5
Classifier: Programming Language :: Python :: 3.6
Classifier: Programming Language :: Python :: 3.7
Classifier: Programming Language :: Python :: 3.8
Classifier: Programming Language :: Python :: 3.9
Classifier: Programming Language :: Python :: 3.10
Classifier: Programming Language :: Python :: 3.11
